yawxt/__init__.py
yawxt/client.py
yawxt/exceptions.py
yawxt/message.py
yawxt/models.py
yawxt/persistence.py
yawxt-0.1.2.dist-info/LICENSE
yawxt-0.1.2.dist-info/METADATA
yawxt-0.1.2.dist-info/WHEEL
yawxt-0.1.2.dist-info/top_level.txt
yawxt-0.1.2.dist-info/RECORD
