Metadata-Version: 2.1
Name: yawxt
Version: 0.1.2
Summary: 又一个微信公众号开发工具箱 Yet Another WeiXin(wechat) Tookit
Home-page: http://github.com/lspvic/yawxt
Author: lspvic
Author-email: lspvic@qq.com
License: MIT License
Keywords: wechat,weixin,Official Account,微信,公众号
Platform: UNKNOWN
Classifier: Intended Audience :: Developers
Classifier: Natural Language :: Chinese (Simplified)
Classifier: License :: OSI Approved :: MIT License
Classifier: Programming Language :: Python :: 2
Classifier: Programming Language :: Python :: 2.6
Classifier: Programming Language :: Python :: 2.7
Classifier: Programming Language :: Python :: 3
Classifier: Programming Language :: Python :: 3.4
Classifier: Programming Language :: Python :: 3.5
Classifier: Programming Language :: Python :: 3.6
Requires-Dist: requests-oauthlib
Requires-Dist: pyOpenSSL ; python_version == "2.6"
